{
  "description": "Lorem ipsum dolor sit amet consectetur adipiscing elit.",
  "readTime": 12,
  "status": "In progress",
  "id": 1762363509787,
  "createdAt": 1762363509606,
  "updatedAt": 1762363509606,
  "title": "Redis Replication Internals",
  "tags": [],
  "slug": "redis-replication-internals-1762363509787",
  "content": {
    "time": 1762363502798,
    "blocks": [
      {
        "id": "XjbC2YS2oI",
        "type": "title",
        "data": {
          "text": "Redis Replication Internals"
        }
      },
      {
        "id": "Otu3rNEpfw",
        "type": "paragraph",
        "data": {
          "text": "Test something new here"
        }
      },
      {
        "id": "43dSbadkFm",
        "type": "table",
        "data": {
          "withHeadings": false,
          "stretched": false,
          "content": [
            [
              "TEst",
              "Lorem ipsum dolor sit amet consectetur adipiscing elit."
            ],
            [
              "Test3",
              "Lorem ipsum dolor sit amet consectetur adipiscing elit."
            ]
          ]
        }
      }
    ],
    "version": "2.31.0-rc.7"
  }
}